npcpy/__init__.py
npcpy/build_funcs.py
npcpy/llm_funcs.py
npcpy/main.py
npcpy/ml_funcs.py
npcpy/npc_array.py
npcpy/npc_compiler.py
npcpy/npc_sysenv.py
npcpy/npcs.py
npcpy/serve.py
npcpy/tools.py
npcpy/data/__init__.py
npcpy/data/audio.py
npcpy/data/data_models.py
npcpy/data/image.py
npcpy/data/load.py
npcpy/data/text.py
npcpy/data/video.py
npcpy/data/web.py
npcpy/ft/__init__.py
npcpy/ft/diff.py
npcpy/ft/ge.py
npcpy/ft/memory_trainer.py
npcpy/ft/model_ensembler.py
npcpy/ft/rl.py
npcpy/ft/sft.py
npcpy/ft/usft.py
npcpy/gen/__init__.py
npcpy/gen/audio_gen.py
npcpy/gen/embeddings.py
npcpy/gen/image_gen.py
npcpy/gen/ocr.py
npcpy/gen/response.py
npcpy/gen/video_gen.py
npcpy/gen/world_gen.py
npcpy/memory/__init__.py
npcpy/memory/command_history.py
npcpy/memory/kg_vis.py
npcpy/memory/knowledge_graph.py
npcpy/memory/memory_processor.py
npcpy/memory/search.py
npcpy/mix/__init__.py
npcpy/mix/debate.py
npcpy/sql/__init__.py
npcpy/sql/ai_function_tools.py
npcpy/sql/database_ai_adapters.py
npcpy/sql/database_ai_functions.py
npcpy/sql/model_runner.py
npcpy/sql/npcsql.py
npcpy/sql/sql_model_compiler.py
npcpy/work/__init__.py
npcpy/work/browser.py
npcpy/work/desktop.py
npcpy/work/plan.py
npcpy/work/trigger.py
npcpy-1.3.20.dist-info/licenses/LICENSE
npcpy-1.3.20.dist-info/METADATA
npcpy-1.3.20.dist-info/WHEEL
npcpy-1.3.20.dist-info/top_level.txt
npcpy-1.3.20.dist-info/RECORD
